metatrain/__init__.py
metatrain/__main__.py
metatrain/_version.py
metatrain/cli/__init__.py
metatrain/cli/eval.py
metatrain/cli/export.py
metatrain/cli/formatter.py
metatrain/cli/train.py
metatrain/deprecated/__init__.py
metatrain/deprecated/nanopet/__init__.py
metatrain/deprecated/nanopet/checkpoints.py
metatrain/deprecated/nanopet/documentation.py
metatrain/deprecated/nanopet/model.py
metatrain/deprecated/nanopet/trainer.py
metatrain/deprecated/nanopet/modules/__init__.py
metatrain/deprecated/nanopet/modules/attention.py
metatrain/deprecated/nanopet/modules/encoder.py
metatrain/deprecated/nanopet/modules/feedforward.py
metatrain/deprecated/nanopet/modules/nef.py
metatrain/deprecated/nanopet/modules/radial_mask.py
metatrain/deprecated/nanopet/modules/structures.py
metatrain/deprecated/nanopet/modules/transformer.py
metatrain/deprecated/nanopet/tests/__init__.py
metatrain/deprecated/nanopet/tests/test_checkpoints.py
metatrain/deprecated/nanopet/tests/test_continue.py
metatrain/deprecated/nanopet/tests/test_exported.py
metatrain/deprecated/nanopet/tests/test_functionality.py
metatrain/deprecated/nanopet/tests/test_regression.py
metatrain/deprecated/nanopet/tests/test_torchscript.py
metatrain/deprecated/nanopet/tests/checkpoints/model-v1_trainer-v1.ckpt.gz
metatrain/deprecated/nanopet/tests/checkpoints/model-v1_trainer-v2.ckpt.gz
metatrain/deprecated/nanopet/tests/checkpoints/model-v1_trainer-v3.ckpt.gz
metatrain/deprecated/nanopet/tests/checkpoints/model-v2_trainer-v2.ckpt.gz
metatrain/deprecated/nanopet/tests/checkpoints/model-v2_trainer-v3.ckpt.gz
metatrain/deprecated/nanopet/tests/checkpoints/model-v3_trainer-v4.ckpt.gz
metatrain/deprecated/nanopet/tests/checkpoints/model-v3_trainer-v5.ckpt.gz
metatrain/deprecated/nanopet/tests/checkpoints/model-v3_trainer-v6.ckpt.gz
metatrain/deprecated/nanopet/tests/checkpoints/model-v3_trainer-v7.ckpt.gz
metatrain/deprecated/nanopet/tests/checkpoints/model-v3_trainer-v8.ckpt.gz
metatrain/experimental/__init__.py
metatrain-2026.1.dist-info/licenses/LICENSE
metatrain-2026.1.dist-info/METADATA
metatrain-2026.1.dist-info/WHEEL
metatrain-2026.1.dist-info/entry_points.txt
metatrain-2026.1.dist-info/top_level.txt
metatrain-2026.1.dist-info/RECORD
