Metadata-Version: 2.4
Name: metatrain
Version: 2026.1
Summary: Training and evaluating machine learning models for atomistic systems.
Author: metatrain developers
License-Expression: BSD-3-Clause
Project-URL: homepage, https://metatensor.github.io/metatrain
Project-URL: documentation, https://metatensor.github.io/metatrain
Project-URL: repository, https://github.com/metatensor/metatrain
Project-URL: issues, https://github.com/metatensor/metatrain/issues
Project-URL: changelog, https://metatensor.github.io/metatrain/latest/dev-docs/changelog.html
Keywords: machine learning,molecular modeling
Classifier: Development Status :: 4 - Beta
Classifier: Intended Audience :: Science/Research
Classifier: Operating System :: POSIX
Classifier: Operating System :: MacOS :: MacOS X
Classifier: Operating System :: Microsoft :: Windows
Classifier: Programming Language :: Python
Classifier: Programming Language :: Python :: 3
Classifier: Topic :: Scientific/Engineering
Classifier: Topic :: Scientific/Engineering :: Bio-Informatics
Classifier: Topic :: Scientific/Engineering :: Chemistry
Classifier: Topic :: Scientific/Engineering :: Physics
Classifier: Topic :: Software Development :: Libraries
Classifier: Topic :: Software Development :: Libraries :: Python Modules
Requires-Python: >=3.10
License-File: LICENSE
Requires-Dist: ase
Requires-Dist: huggingface_hub
Requires-Dist: numpy
Requires-Dist: metatensor-learn<0.5,>=0.4.0
Requires-Dist: metatensor-operations<0.5,>=0.4.0
Requires-Dist: metatensor-torch<0.9,>=0.8.2
Requires-Dist: metatomic-torch<0.2,>=0.1.7
Requires-Dist: jsonschema
Requires-Dist: pydantic>=2.12
Requires-Dist: typing_extensions
Requires-Dist: omegaconf>=2.3.0
Requires-Dist: python-hostlist
Requires-Dist: tqdm
Requires-Dist: vesin
Provides-Extra: soap-bpnn
Requires-Dist: torch-spex<0.2,>=0.1; extra == "soap-bpnn"
Requires-Dist: wigners; extra == "soap-bpnn"
Provides-Extra: pet
Provides-Extra: nanopet
Provides-Extra: gap
Requires-Dist: featomic-torch<0.8,>=0.7; extra == "gap"
Requires-Dist: skmatter; extra == "gap"
Requires-Dist: scipy; extra == "gap"
Provides-Extra: llpr
Provides-Extra: mace
Requires-Dist: mace-torch>=0.3.14; extra == "mace"
Requires-Dist: e3nn; extra == "mace"
Dynamic: license-file
